[
    {
        "age": 0, 
        "id": 1, 
        "orders": [ 
            {
                "name": "Bela jagoda",
                "quantity": "1"
            },
            {
                "name": "Bel bor",
                "quantity": "5"
            }
        ],
        "price": 1800,
        "cust_name": "Stefan",
        "cust_lname": "Tasic",
        "cust_adress": "Dubocica 8",
        "cust_post": "16000",
        "cust_city": "Leskovac",
        "cust_phone": "0654437578",
        "cust_email": "steftas@gmai.com",
        "date": "08.08.2016",
        "seen": false
    }, 
    {
        "age": 1, 
        "id": 2, 
        "orders": [ 
            {
                "name": "Bela jagoda",
                "quantity": "11"
            },
            {
                "name": "Bel bor",
                "quantity": "20"
            },
            {
                "name": "Paulovnija",
                "quantity": "11"
            },
            {
                "name": "Bel bor",
                "quantity": "20"
            }
        ],
        "price": 12500,
        "cust_name": "Stefan",
        "cust_lname": "Tasic",
        "cust_adress": "Dubocica 8",
        "cust_post": "16000",
        "cust_city": "Leskovac",
        "cust_phone": "0654437578",
        "cust_email": "steftas@gmai.com",
        "date": "18.08.2016",
        "seen": false
    },
    {
        "age": 2, 
        "id": 3, 
        "orders": [ 
            {
                "name": "Bela jagoda",
                "quantity": "1"
            },
            {
                "name": "Bel bor",
                "quantity": "17"
            }
        ],
        "price": 20150,
        "cust_name": "Stefan",
        "cust_lname": "Tasic",
        "cust_adress": "Dubocica 8",
        "cust_post": "16000",
        "cust_city": "Leskovac",
        "cust_phone": "0654437578",
        "cust_email": "steftas@gmai.com",
        "date": "31.08.2016",
        "seen": true
    }
]
